minijinja-2.14.0.dist-info/METADATA
minijinja-2.14.0.dist-info/WHEEL
minijinja-2.14.0.dist-info/licenses/LICENSE
minijinja/__init__.py
minijinja/__init__.pyi
minijinja/_internal.py
minijinja/_lowlevel.pyd
minijinja/_lowlevel.pyi
minijinja-2.14.0.dist-info/RECORD
